{
    "sliderImg"  : [
        {
            "srno": "1",
            "name":"wcersc",
            "url": "images/slider/2.jpg"
        },
        {
            "srno": "2",
            "name":"wcersc",
            "url": "images/slider/3.jpg"
        },
        {
            "srno": "3",
            "name":"wcersc",
            "url": "images/slider/4.jpg"
        },
        {
            "srno": "4",
            "name":"wcersc",
            "url": "images/slider/5.jpg"
        },
        {
            "srno": "5",
            "name":"wcersc",
            "url": "images/slider/6.jpg"
        },
        {
            "srno": "6",
            "name":"wcersc",
            "url": "images/slider/7.jpg"
        }
    ],

    "homePage" : [
        {
            "type": "Published by",
            "url": "../../../images/publication/Springer.jpg"
        },
        {
            "type": "paperSubmission",
            "url": "../../../images/publication/chair.png"
        }
    ],

    "support":[
        {
            "name":"WCE ACM",
            "url":"images/wceacm.png"
        }

    ],
    "paperSubmissionTemplate":"/images/Sub.jpg",
    "posterSubmission":"images/poster.png"
    
}